kafman/.version
kafman/__classpath__.py
kafman/__init__.py
kafman/__main__.py
kafman/welcome.txt
kafman/core/__init__.py
kafman/core/constants.py
kafman/core/kafka_message.py
kafman/core/statistics_worker.py
kafman/core/consumer/__init__.py
kafman/core/consumer/consumer_config.py
kafman/core/consumer/consumer_worker.py
kafman/core/exception/__init__.py
kafman/core/exception/exceptions.py
kafman/core/producer/__init__.py
kafman/core/producer/producer_config.py
kafman/core/producer/producer_worker.py
kafman/core/schema/__init__.py
kafman/core/schema/kafka_schema.py
kafman/core/schema/plain_schema.py
kafman/core/schema/registry_subject.py
kafman/core/schema/schema_factory.py
kafman/core/schema/schema_field.py
kafman/core/schema/schema_registry.py
kafman/core/schema/schema_type.py
kafman/core/schema/widget_utils.py
kafman/core/schema/avro/__init__.py
kafman/core/schema/avro/avro_schema.py
kafman/core/schema/avro/avro_type.py
kafman/core/schema/avro/field/__init__.py
kafman/core/schema/avro/field/array_field.py
kafman/core/schema/avro/field/enum_field.py
kafman/core/schema/avro/field/field_factory.py
kafman/core/schema/avro/field/fixed_field.py
kafman/core/schema/avro/field/map_field.py
kafman/core/schema/avro/field/primitive_field.py
kafman/core/schema/avro/field/record_field.py
kafman/core/schema/json/__init__.py
kafman/core/schema/json/json_parser.py
kafman/core/schema/json/json_schema.py
kafman/core/schema/json/json_type.py
kafman/core/schema/json/property/__init__.py
kafman/core/schema/json/property/array_property.py
kafman/core/schema/json/property/enum_property.py
kafman/core/schema/json/property/object_property.py
kafman/core/schema/json/property/primitive_property.py
kafman/core/schema/json/property/property.py
kafman/core/schema/json/property/property_factory.py
kafman/resources/app-icon.png
kafman/resources/application.properties
kafman/resources/consumer-settings.properties
kafman/resources/producer-settings.properties
hspylib_kafman-0.9.152.dist-info/METADATA
hspylib_kafman-0.9.152.dist-info/WHEEL
hspylib_kafman-0.9.152.dist-info/top_level.txt
hspylib_kafman-0.9.152.dist-info/RECORD
