Metadata-Version: 2.1
Name: hspylib-kafman
Version: 0.9.152
Summary: HsPyLib - Apache Kafka Manager
Home-page: https://github.com/yorevs/hspylib
Author: Hugo Saporetti Junior
Author-email: yorevs@hotmail.com
License: MIT
Project-URL: GitHub, https://github.com/yorevs/hspylib
Project-URL: PyPi, https://pypi.org/project/hspylib-kafman/
Keywords: apache,kafka,queue,manager,application
Platform: Darwin
Platform: Linux
Classifier: License :: OSI Approved :: MIT License
Classifier: Programming Language :: Python :: 3.10
Classifier: Operating System :: MacOS :: MacOS X
Classifier: Operating System :: POSIX :: Linux
Classifier: Operating System :: Unix
Classifier: Development Status :: 4 - Beta
Classifier: Environment :: X11 Applications :: Qt
Classifier: Natural Language :: English
Classifier: Topic :: Desktop Environment
Classifier: Intended Audience :: Developers
Requires-Python: >=3.10
Requires-Dist: hspylib
Requires-Dist: hspylib-hqt
Requires-Dist: requests >=2.32.3
Requires-Dist: urllib3 >=1.26.20
Requires-Dist: PyQt5 >=5.15.10
Requires-Dist: PyQt5-stubs >=5.15.6.0
Requires-Dist: confluent-kafka >=2.5.0
Requires-Dist: fastavro >=1.9.5
Requires-Dist: jsonschema >=4.23.0
Requires-Dist: avro-python3 >=1.10.2
